LuaStakky/AdminPanel.py
LuaStakky/BaseModule.py
LuaStakky/ConfigGenerators.py
LuaStakky/ContainerController.py
LuaStakky/Exeptions.py
LuaStakky/FsController.py
LuaStakky/LuaConfigModule.py
LuaStakky/Nginx.py
LuaStakky/Tarantool.py
LuaStakky/TarantoolAppBuilder.py
LuaStakky/Utils.py
LuaStakky/__init__.py
LuaStakky/__main__.py
LuaStakky/default.yaml
LuaStakky-0.1.1.dist-info/LICENSE
LuaStakky-0.1.1.dist-info/METADATA
LuaStakky-0.1.1.dist-info/WHEEL
LuaStakky-0.1.1.dist-info/entry_points.txt
LuaStakky-0.1.1.dist-info/top_level.txt
LuaStakky-0.1.1.dist-info/RECORD
