Metadata-Version: 2.1
Name: LuaStakky
Version: 0.1.1
Summary: Full stack lua web framework
Home-page: https://github.com/LuaStakky/LuaStakky
Author: Artem3213212
Author-email: artem@agteam.dev
License: UNKNOWN
Project-URL: Bug Tracker, https://github.com/LuaStakky/LuaStakky/issues
Platform: UNKNOWN
Classifier: Development Status :: 3 - Alpha
Classifier: Intended Audience :: Developers
Classifier: Intended Audience :: Information Technology
Classifier: Intended Audience :: System Administrators
Classifier: License :: OSI Approved :: MIT License
Classifier: Operating System :: POSIX :: Linux
Classifier: Programming Language :: Other
Classifier: Topic :: Internet :: WWW/HTTP :: Site Management
Classifier: Topic :: Software Development
Classifier: Topic :: Software Development :: Build Tools
Classifier: Topic :: Software Development :: Code Generators
Classifier: Topic :: Software Development :: Libraries
Classifier: Topic :: Software Development :: Libraries :: Application Frameworks
Requires-Python: >=3.6
Requires-Dist: luaparser (>=3.0.0)
Requires-Dist: gitignore-parser (>=0.0.8)
Requires-Dist: HiYaPyCo (>=0.4.16)
Requires-Dist: docker-compose (>=1.28.5)
